lagent/__init__.py
lagent/schema.py
lagent/version.py
lagent/actions/__init__.py
lagent/actions/action_executor.py
lagent/actions/arxiv_search.py
lagent/actions/base_action.py
lagent/actions/bing_browser.py
lagent/actions/bing_map.py
lagent/actions/builtin_actions.py
lagent/actions/google_scholar_search.py
lagent/actions/google_search.py
lagent/actions/ipython_interactive.py
lagent/actions/ipython_interpreter.py
lagent/actions/ipython_manager.py
lagent/actions/parser.py
lagent/actions/ppt.py
lagent/actions/python_interpreter.py
lagent/agents/__init__.py
lagent/agents/autogpt.py
lagent/agents/base_agent.py
lagent/agents/internlm2_agent.py
lagent/agents/react.py
lagent/agents/rewoo.py
lagent/llms/__init__.py
lagent/llms/base_api.py
lagent/llms/base_llm.py
lagent/llms/huggingface.py
lagent/llms/lmdeploy_wrapper.py
lagent/llms/meta_template.py
lagent/llms/openai.py
lagent/llms/sensenova.py
lagent/llms/vllm_wrapper.py
lagent/utils/__init__.py
lagent/utils/gen_key.py
lagent/utils/package.py
lagent/utils/util.py
lagent-0.2.4.data/data/README.md
lagent-0.2.4.dist-info/LICENSE
lagent-0.2.4.dist-info/METADATA
lagent-0.2.4.dist-info/WHEEL
lagent-0.2.4.dist-info/top_level.txt
lagent-0.2.4.dist-info/RECORD
