Metadata-Version: 2.1
Name: lagent
Version: 0.2.4
Summary: A lightweight framework for building LLM-based agents
Home-page: https://github.com/InternLM/lagent
License: Apache 2.0
Keywords: artificial general intelligence,agent,agi,llm
Platform: UNKNOWN
Requires-Dist: arxiv
Requires-Dist: distro
Requires-Dist: duckduckgo-search ==5.3.1b1
Requires-Dist: filelock
Requires-Dist: func-timeout
Requires-Dist: griffe <1.0
Requires-Dist: json5
Requires-Dist: jsonschema
Requires-Dist: jupyter
Requires-Dist: jupyter-client
Requires-Dist: phx-class-registry ==4.1.0
Requires-Dist: requests
Requires-Dist: streamlit
Requires-Dist: termcolor
Requires-Dist: tiktoken
Requires-Dist: timeout-decorator
Requires-Dist: typing-extensions
Provides-Extra: all
Requires-Dist: google-search-results ; extra == 'all'
Requires-Dist: lmdeploy >=0.2.5 ; extra == 'all'
Requires-Dist: pillow ; extra == 'all'
Requires-Dist: python-pptx ; extra == 'all'
Requires-Dist: timeout-decorator ; extra == 'all'
Requires-Dist: torch ; extra == 'all'
Requires-Dist: transformers <=4.40,>=4.34 ; extra == 'all'
Requires-Dist: vllm >=0.3.3 ; extra == 'all'
Requires-Dist: arxiv ; extra == 'all'
Requires-Dist: distro ; extra == 'all'
Requires-Dist: duckduckgo-search ==5.3.1b1 ; extra == 'all'
Requires-Dist: filelock ; extra == 'all'
Requires-Dist: func-timeout ; extra == 'all'
Requires-Dist: griffe <1.0 ; extra == 'all'
Requires-Dist: json5 ; extra == 'all'
Requires-Dist: jsonschema ; extra == 'all'
Requires-Dist: jupyter ; extra == 'all'
Requires-Dist: jupyter-client ; extra == 'all'
Requires-Dist: phx-class-registry ==4.1.0 ; extra == 'all'
Requires-Dist: requests ; extra == 'all'
Requires-Dist: streamlit ; extra == 'all'
Requires-Dist: termcolor ; extra == 'all'
Requires-Dist: tiktoken ; extra == 'all'
Requires-Dist: typing-extensions ; extra == 'all'
Provides-Extra: optional
Requires-Dist: google-search-results ; extra == 'optional'
Requires-Dist: lmdeploy >=0.2.5 ; extra == 'optional'
Requires-Dist: pillow ; extra == 'optional'
Requires-Dist: python-pptx ; extra == 'optional'
Requires-Dist: timeout-decorator ; extra == 'optional'
Requires-Dist: torch ; extra == 'optional'
Requires-Dist: transformers <=4.40,>=4.34 ; extra == 'optional'
Requires-Dist: vllm >=0.3.3 ; extra == 'optional'
